CHANGELOG.rst
LICENSE
MANIFEST.in
README.rst
setup.py
commentator/__init__.py
commentator/admin.py
commentator/default.py
commentator/forms.py
commentator/managers.py
commentator/models.py
commentator/urls.py
commentator/utils.py
commentator/views.py
commentator/locale/en/LC_MESSAGES/django.mo
commentator/locale/en/LC_MESSAGES/django.po
commentator/locale/ru/LC_MESSAGES/django.mo
commentator/locale/ru/LC_MESSAGES/django.po
commentator/migrations/0001_initial.py
commentator/migrations/0001_initial.pyc
commentator/migrations/0002_threadview.py
commentator/migrations/0002_threadview.pyc
commentator/migrations/__init__.py
commentator/migrations/__init__.pyc
commentator/static/.DS_Store
commentator/static/commentator/css/default.css
commentator/static/commentator/css/lib/jquery.jgrowl.css
commentator/static/commentator/editor/editor.css
commentator/static/commentator/editor/editor.png
commentator/static/commentator/editor/editor1x.png
commentator/static/commentator/editor/editor2x.png
commentator/static/commentator/editor/editor4x.png
commentator/static/commentator/editor/jquery.markitup.js
commentator/static/commentator/img/loading.gif
commentator/static/commentator/img/refresh.gif
commentator/static/commentator/js/default.coffee
commentator/static/commentator/js/default.js
commentator/static/commentator/js/default.js.map
commentator/static/commentator/js/lib/jquery-1.10.2.min.map
commentator/static/commentator/js/lib/jquery.form.min.js
commentator/static/commentator/js/lib/jquery.jgrowl.min.js
commentator/static/commentator/js/lib/jquery.min.js
commentator/static/commentator/js/lib/jquery.sisyphus.min.js
commentator/static/commentator/js/lib/prettify/prettify.css
commentator/static/commentator/js/lib/prettify/prettify.js
commentator/templates/commentator/comment_body.html
commentator/templates/commentator/comment_form.html
commentator/templates/commentator/comment_wrapper.html
commentator/templates/commentator/commentator_login.html
django_commentator.egg-info/PKG-INFO
django_commentator.egg-info/SOURCES.txt
django_commentator.egg-info/dependency_links.txt
django_commentator.egg-info/requires.txt
django_commentator.egg-info/top_level.txt