Metadata-Version: 1.1
Name: django-commentator
Version: 0.0.4
Summary: Commentaries system for Django
Home-page: https://github.com/smidth/django-commentator
Author: Alex Vakhitov
Author-email: alex.vakhitov@gmail.com
License: MIT
Platform: UNKNOWN
Classifier: Development Status :: 4 - Beta
Classifier: Environment :: Web Environment
Classifier: Intended Audience :: Developers
Classifier: License :: OSI Approved :: BSD License
Classifier: Operating System :: OS Independent
Classifier: Programming Language :: Python
Classifier: Framework :: Django
